qau/__init__.py
qau/appium_utils/__init__.py
qau/logging_utils/__init__.py
qau/logging_utils/setup.py
qau/playwright_utils/__init__.py
qau/playwright_utils/get_api_response.py
qau/playwright_utils/get_authentication_number.py
qau/playwright_utils/get_iframe_page.py
qau/playwright_utils/mock_api.py
qau/playwright_utils/scroll_to_visible.py
qau/playwright_utils/sibling_util.py
qau/termux/__init__.py
qau/termux/adb.py
qau/termux/sms.py
qa_util-0.0.0.dist-info/METADATA
qa_util-0.0.0.dist-info/WHEEL
qa_util-0.0.0.dist-info/top_level.txt
qa_util-0.0.0.dist-info/RECORD
