Metadata-Version: 2.4
Name: qa-util
Version: 0.0.0
Summary: will be replaced soon.
Author-email: Wooyoung <andy241822@gmail.com>
License: MIT
Requires-Python: >=3.9
Requires-Dist: pytest>=8.4.2
Requires-Dist: pytest-playwright>=0.7.0
Requires-Dist: exceptiongroup>=1.3.0
Requires-Dist: rich>=13.0
